capital/__init__.py
capital/client.py
capital/examples.py
capital/exceptions.py
capital/variables.py
python_capital-0.2.2.dist-info/METADATA
python_capital-0.2.2.dist-info/WHEEL
python_capital-0.2.2.dist-info/licenses/LICENSE
python_capital-0.2.2.dist-info/RECORD
