Metadata-Version: 2.4
Name: python-capital
Version: 0.2.2
Summary: A simple wrapper for capital.com exchange API
Project-URL: Homepage, https://github.com/iribeirocampos/python-capital
Project-URL: Bug Tracker, https://github.com/iribeirocampos/python-capital/issues
Author-email: Iuri Campos <iuri.campos@tecnico.ulisboa.pt>
License: MIT
License-File: LICENSE
Classifier: License :: OSI Approved :: MIT License
Classifier: Operating System :: OS Independent
Classifier: Programming Language :: Python :: 3
Requires-Python: >=3.7
Requires-Dist: pycryptodome
Requires-Dist: requests>=2.25.1
